csmarketapi/__init__.py
csmarketapi/csmarketapi.py
csmarketapi/enums.py
csmarketapi/models.py
csmarketapi_client-1.0.0.dist-info/licenses/LICENSE
csmarketapi_client-1.0.0.dist-info/METADATA
csmarketapi_client-1.0.0.dist-info/WHEEL
csmarketapi_client-1.0.0.dist-info/top_level.txt
csmarketapi_client-1.0.0.dist-info/RECORD
