Metadata-Version: 2.4
Name: csmarketapi-client
Version: 1.0.0
Summary: API client for CSMarketAPI from csInvest
Author-email: Luis <luis@softwerk.ai>
License-Expression: MIT
Project-URL: Homepage, https://github.com/softwerk-org/csmarketapi-client
Project-URL: Issues, https://github.com/softwerk-org/csmarketapi-client/issues
Classifier: Programming Language :: Python :: 3
Classifier: Operating System :: OS Independent
Requires-Python: >=3.13
License-File: LICENSE
Requires-Dist: dotenv>=0.9.9
Requires-Dist: httpx>=0.28.1
Requires-Dist: pydantic>=2.11.7
Requires-Dist: pytest>=8.4.1
Requires-Dist: pytest-asyncio>=1.1.0
Dynamic: license-file
